foursquare_swarm_ical/__init__.py
foursquare_swarm_ical/__main__.py
foursquare_swarm_ical/cli.py
foursquare_swarm_ical/config_file.py
foursquare_swarm_ical/db.py
foursquare_swarm_ical/emoji.py
foursquare_swarm_ical/emoji.yaml
foursquare_swarm_ical/ical.py
foursquare_swarm_ical/py.typed
foursquare_swarm_ical-1.0.3.dist-info/LICENSE
foursquare_swarm_ical-1.0.3.dist-info/METADATA
foursquare_swarm_ical-1.0.3.dist-info/WHEEL
foursquare_swarm_ical-1.0.3.dist-info/entry_points.txt
foursquare_swarm_ical-1.0.3.dist-info/top_level.txt
foursquare_swarm_ical-1.0.3.dist-info/RECORD
