Metadata-Version: 2.1
Name: foursquare-swarm-ical
Version: 1.0.3
Summary: Sync Foursquare Swarm check-ins to local sqlite DB and generate iCalendar
Author-email: Tomáš Janoušek <tomi@nomi.cz>
License: MIT
Project-URL: Homepage, https://github.com/liskin/foursquare-swarm-ical
Project-URL: Release Notes, https://github.com/liskin/foursquare-swarm-ical/releases
Project-URL: Issues, https://github.com/liskin/foursquare-swarm-ical/issues
Project-URL: CI, https://github.com/liskin/foursquare-swarm-ical/actions
Project-URL: Donations (GitHub), https://github.com/sponsors/liskin
Project-URL: Donations (PayPal), https://www.paypal.me/lisknisi/5EUR
Classifier: Development Status :: 5 - Production/Stable
Classifier: Environment :: Console
Classifier: Programming Language :: Python :: 3.8
Classifier: Programming Language :: Python :: 3.9
Classifier: Programming Language :: Python :: 3.10
Classifier: Programming Language :: Python :: 3.11
Classifier: Programming Language :: Python :: 3.12
Classifier: License :: OSI Approved :: MIT License
Classifier: Operating System :: OS Independent
Classifier: Topic :: Utilities
Requires-Python: ~=3.8
License-File: LICENSE
Requires-Dist: PyYAML
Requires-Dist: click ~=8.0
Requires-Dist: click-config-file
Requires-Dist: foursquare
Requires-Dist: icalendar >=5.0.2
Requires-Dist: platformdirs >=2.1
Requires-Dist: importlib-metadata ; python_version < "3.10"
Requires-Dist: importlib-resources ; python_version < "3.9"
Provides-Extra: dev
Requires-Dist: build >=0.7 ; extra == 'dev'
Requires-Dist: flake8 ; extra == 'dev'
Requires-Dist: isort >=5.0 ; extra == 'dev'
Requires-Dist: mypy >=0.900 ; extra == 'dev'
Requires-Dist: prysk >=0.20.0 ; extra == 'dev'
Requires-Dist: twine ; extra == 'dev'
Requires-Dist: types-PyYAML ; extra == 'dev'
Requires-Dist: types-pytz ; extra == 'dev'
Provides-Extra: test
Requires-Dist: pytest ; extra == 'test'
Requires-Dist: pytest-recording ; extra == 'test'
